gocept.webtoken-4.0-py3.11-nspkg.pth
gocept/webtoken/__init__.py
gocept/webtoken/header.py
gocept/webtoken/interfaces.py
gocept/webtoken/keys.py
gocept/webtoken/token.py
gocept/webtoken/testing/keys/jwt-access
gocept/webtoken/testing/keys/jwt-access.pub
gocept/webtoken/testing/keys/jwt-application
gocept/webtoken/testing/keys/jwt-application.pub
gocept/webtoken/testing/keys/key1
gocept/webtoken/testing/keys/key1.pub
gocept/webtoken/tests/__init__.py
gocept/webtoken/tests/conftest.py
gocept/webtoken/tests/test_doctest.py
gocept/webtoken/tests/test_endtoend.py
gocept/webtoken/tests/test_header.py
gocept/webtoken/tests/test_keys.py
gocept/webtoken/tests/test_token.py
gocept.webtoken-4.0.dist-info/LICENSE.txt
gocept.webtoken-4.0.dist-info/METADATA
gocept.webtoken-4.0.dist-info/WHEEL
gocept.webtoken-4.0.dist-info/namespace_packages.txt
gocept.webtoken-4.0.dist-info/top_level.txt
gocept.webtoken-4.0.dist-info/RECORD
