Metadata-Version: 2.1
Name: gocept.webtoken
Version: 4.0
Summary: Wrapper around JWT tokens and the Zope Component Architecture (ZCA).
Home-page: https://github.com/gocept/gocept.webtoken
Author: gocept <mail@gocept.com>
Author-email: mail@gocept.com
License: MIT
Keywords: jwt token webtoken ZCA
Classifier: Development Status :: 4 - Beta
Classifier: Intended Audience :: Developers
Classifier: Natural Language :: English
Classifier: Operating System :: OS Independent
Classifier: Topic :: Internet :: WWW/HTTP
Classifier: Topic :: Internet :: WWW/HTTP :: Browsers
Classifier: Topic :: Security
Classifier: Topic :: Security :: Cryptography
Classifier: Topic :: Software Development
Classifier: Topic :: Software Development :: Libraries
Classifier: Topic :: Software Development :: Libraries :: Python Modules
Classifier: License :: OSI Approved
Classifier: License :: OSI Approved :: MIT License
Classifier: Programming Language :: Python
Classifier: Programming Language :: Python :: 3
Classifier: Programming Language :: Python :: 3.6
Classifier: Programming Language :: Python :: 3.7
Classifier: Programming Language :: Python :: 3.8
Classifier: Programming Language :: Python :: 3.9
Classifier: Programming Language :: Python :: 3.10
Classifier: Programming Language :: Python :: 3.11
Classifier: Programming Language :: Python :: Implementation
Classifier: Programming Language :: Python :: Implementation :: CPython
Classifier: Programming Language :: Python :: Implementation :: PyPy
Requires-Python: >=3.7
License-File: LICENSE.txt
Requires-Dist: cryptography
Requires-Dist: pyjwt (>=2)
Requires-Dist: setuptools
Requires-Dist: zope.interface
Requires-Dist: zope.component
